pychatgpt_gui/__init__.py
pychatgpt_gui/api.py
pychatgpt_gui/app.py
pychatgpt_gui/pygpt4all_cli.py
pychatgpt_gui/utils.py
pychatgpt_gui/voice_bot.py
pychatgpt_gui-0.0.1.dist-info/METADATA
pychatgpt_gui-0.0.1.dist-info/WHEEL
pychatgpt_gui-0.0.1.dist-info/top_level.txt
pychatgpt_gui-0.0.1.dist-info/RECORD
