Metadata-Version: 2.1
Name: pychatgpt-gui
Version: 0.0.1
Summary: pyChatGPT GUI - is an open-source, low-code python GUI wrapper providing easy access and swift usage of Large Language Models (LLMs) such as ChatGPT, AutoGPT, LLaMa, GPT-J, and GPT4All with custom-data and pre-trained inferences.
Home-page: https://github.com/ajayarunachalam/pychatgpt_gui
Author: Ajay Arunachalam
Author-email: ajay.arunachalam08@gmail.com
License: MIT
Requires-Dist: numpy
Requires-Dist: pandas
Requires-Dist: warnings
Requires-Dist: scipy
Requires-Dist: tqdm
Requires-Dist: openai
Requires-Dist: gpt-index (==0.4.24)
Requires-Dist: PyPDF2
Requires-Dist: PyCryptodome
Requires-Dist: gradio
Requires-Dist: scikit-learn
Requires-Dist: openai-whisper
Requires-Dist: TTS
Requires-Dist: gTTS
Requires-Dist: ffmpeg
Requires-Dist: ffprobe
Requires-Dist: SpeechRecognition
Requires-Dist: pyaudio
Requires-Dist: playsound
Requires-Dist: langchain
Requires-Dist: chromadb
Requires-Dist: tiktoken
Requires-Dist: pypdf
Requires-Dist: unstructured[local-inference]
Requires-Dist: nomic
Requires-Dist: pyllamacpp
Requires-Dist: pygpt4all
